znail/__init__.py
znail/update.py
znail/version.py
znail/netem/__init__.py
znail/netem/disciplines.py
znail/netem/dnsoverride.py
znail/netem/healthcheck.py
znail/netem/ipredirect.py
znail/netem/tc.py
znail/netem/tcpdump.py
znail/netem/usb.py
znail/netem/util.py
znail/netem/data/README.md
znail/netem/data/hub-ctrl
znail/ui/__init__.py
znail/ui/__main__.py
znail/ui/util.py
znail/ui/api/__init__.py
znail/ui/api/capture.py
znail/ui/api/disconnect.py
znail/ui/api/dnsoverride.py
znail/ui/api/healthcheck.py
znail/ui/api/ipredirect.py
znail/ui/api/reboot.py
znail/ui/api/whitelist.py
znail/ui/api/disciplines/__init__.py
znail/ui/api/disciplines/packet_corruption.py
znail/ui/api/disciplines/packet_delay.py
znail/ui/api/disciplines/packet_duplication.py
znail/ui/api/disciplines/packet_loss.py
znail/ui/api/disciplines/packet_rate_control.py
znail/ui/api/disciplines/packet_reordering.py
znail/ui/web/__init__.py
znail/ui/web/views.py
znail/ui/web/static/bootstrap.min.css
znail/ui/web/static/bootstrap.min.js
znail/ui/web/static/dashboard.css
znail/ui/web/static/jquery-3.2.1.slim.min.js
znail/ui/web/static/mermaid.min.js
znail/ui/web/static/popper.min.js
znail/ui/web/templates/about.html
znail/ui/web/templates/base.html
znail/ui/web/templates/health.html
znail/ui/web/templates/index.html
znail/ui/web/templates/network_capture.html
znail/ui/web/templates/network_disconnect.html
znail/ui/web/templates/network_dnsoverride.html
znail/ui/web/templates/network_ip_redirect.html
znail/ui/web/templates/network_whitelist.html
znail/ui/web/templates/packet_corruption.html
znail/ui/web/templates/packet_delay.html
znail/ui/web/templates/packet_duplication.html
znail/ui/web/templates/packet_loss.html
znail/ui/web/templates/packet_rate_control.html
znail/ui/web/templates/packet_reordering.html
znail-0.5.0.dist-info/DESCRIPTION.rst
znail-0.5.0.dist-info/METADATA
znail-0.5.0.dist-info/RECORD
znail-0.5.0.dist-info/WHEEL
znail-0.5.0.dist-info/entry_points.txt
znail-0.5.0.dist-info/metadata.json
znail-0.5.0.dist-info/top_level.txt
