Metadata-Version: 2.0
Name: znail
Version: 0.5.0
Summary: Network Emulator
Home-page: https://github.com/znailnetem/znail
Maintainer: Andreas Nilsson
Maintainer-email: andni233@gmail.com
License: Apache License 2.0
Keywords: znail
Platform: UNKNOWN
Classifier: Development Status :: 4 - Beta
Classifier: Intended Audience :: Developers
Classifier: Topic :: System :: Networking
Classifier: Topic :: System :: Emulators
Classifier: Topic :: Software Development :: Quality Assurance
Classifier: Topic :: Software Development :: Testing
Classifier: License :: OSI Approved :: Apache Software License
Classifier: Programming Language :: Python :: 3.5
